chronocalc.py
chronocalc-0.9.1.data/data/share/doc/chronocalc/README.rst
chronocalc-0.9.1.dist-info/METADATA
chronocalc-0.9.1.dist-info/WHEEL
chronocalc-0.9.1.dist-info/entry_points.txt
chronocalc-0.9.1.dist-info/licenses/COPYING.WTFPL
chronocalc-0.9.1.dist-info/RECORD
