Metadata-Version: 2.1
Name: chronocalc
Version: 0.9.1
Summary: chronocalc - a date/time/duration calculator
Project-URL: Homepage, https://gitlab.com/hydrargyrum/timecalc
Author-email: Hg <dev@indigo.re>
License-Expression: WTFPL
License-File: COPYING.WTFPL
Keywords: calculator,compute,date,datetime,duration,evaluate,repl,time
Requires-Python: >=3
Requires-Dist: python-dateutil
